smolhub_download/__init__.py
smolhub_download/client.py
smolhub_download/utils.py
smolhub_download-0.1.4.dist-info/METADATA
smolhub_download-0.1.4.dist-info/WHEEL
smolhub_download-0.1.4.dist-info/top_level.txt
smolhub_download-0.1.4.dist-info/RECORD
