Metadata-Version: 2.2
Name: smolhub_download
Version: 0.1.4
Summary: A Python client for downloading models and datasets from SmolHub via Supabase
Home-page: https://github.com/smolhub/smolhub_download
Author: SmolHub
Author-email: contact@smolhub.com
Classifier: Development Status :: 3 - Alpha
Classifier: Intended Audience :: Developers
Classifier: License :: OSI Approved :: MIT License
Classifier: Operating System :: OS Independent
Classifier: Programming Language :: Python :: 3
Classifier: Programming Language :: Python :: 3.7
Classifier: Programming Language :: Python :: 3.8
Classifier: Programming Language :: Python :: 3.9
Classifier: Programming Language :: Python :: 3.10
Classifier: Programming Language :: Python :: 3.11
Classifier: Topic :: Software Development :: Libraries :: Python Modules
Classifier: Topic :: Software Development :: Libraries
Requires-Python: >=3.7
Requires-Dist: requests>=2.25.0
Requires-Dist: torch>=1.7.0
Requires-Dist: requests_toolbelt
Requires-Dist: tqdm
Dynamic: author
Dynamic: author-email
Dynamic: classifier
Dynamic: description
Dynamic: description-content-type
Dynamic: home-page
Dynamic: requires-dist
Dynamic: requires-python
Dynamic: summary
